jupyterlab_hubshare/__init__.py
jupyterlab_hubshare/_version.py
jupyterlab_hubshare/handlers.py
jupyterlab_hubshare/labextension/package.json
jupyterlab_hubshare/labextension/static/747.c6b4e810358510fbc2b0.js
jupyterlab_hubshare/labextension/static/777.70eb56c5ff48a14a1388.js
jupyterlab_hubshare/labextension/static/remoteEntry.fb1a4c86444af3989332.js
jupyterlab_hubshare/labextension/static/style.js
jupyterlab_hubshare/labextension/static/third-party-licenses.json
jupyterlab_hubshare-0.3.0.data/data/etc/jupyter/jupyter_server_config.d/jupyterlab_hubshare.json
jupyterlab_hubshare-0.3.0.data/data/share/jupyter/labextensions/jupyterlab_hubshare/install.json
jupyterlab_hubshare-0.3.0.data/data/share/jupyter/labextensions/jupyterlab_hubshare/package.json
jupyterlab_hubshare-0.3.0.data/data/share/jupyter/labextensions/jupyterlab_hubshare/static/747.c6b4e810358510fbc2b0.js
jupyterlab_hubshare-0.3.0.data/data/share/jupyter/labextensions/jupyterlab_hubshare/static/777.70eb56c5ff48a14a1388.js
jupyterlab_hubshare-0.3.0.data/data/share/jupyter/labextensions/jupyterlab_hubshare/static/remoteEntry.fb1a4c86444af3989332.js
jupyterlab_hubshare-0.3.0.data/data/share/jupyter/labextensions/jupyterlab_hubshare/static/style.js
jupyterlab_hubshare-0.3.0.data/data/share/jupyter/labextensions/jupyterlab_hubshare/static/third-party-licenses.json
jupyterlab_hubshare-0.3.0.dist-info/LICENSE
jupyterlab_hubshare-0.3.0.dist-info/METADATA
jupyterlab_hubshare-0.3.0.dist-info/WHEEL
jupyterlab_hubshare-0.3.0.dist-info/top_level.txt
jupyterlab_hubshare-0.3.0.dist-info/RECORD
