Metadata-Version: 2.1
Name: jupyterlab-hubshare
Version: 0.3.0
Summary: share notebooks on jupyterhub
Home-page: https://github.com/lydian/jupyterlab_hubshare
Author: Lydian Lee
Author-email: lydianly@gmail.com
License: BSD-3-Clause
Keywords: Jupyter,JupyterLab,JupyterLab3
Platform: Linux
Platform: Mac OS X
Platform: Windows
Classifier: License :: OSI Approved :: BSD License
Classifier: Programming Language :: Python
Classifier: Programming Language :: Python :: 3
Classifier: Programming Language :: Python :: 3.6
Classifier: Programming Language :: Python :: 3.7
Classifier: Programming Language :: Python :: 3.8
Classifier: Programming Language :: Python :: 3.9
Classifier: Framework :: Jupyter
Requires-Python: >=3.6
Requires-Dist: jupyterlab (~=3.0)
Requires-Dist: nbconvert
Requires-Dist: nbformat
Requires-Dist: tornado
Requires-Dist: jupyter-server
Requires-Dist: IPython
